cybory/__init__.py
cybory-0.0.1.dist-info/LICENSE
cybory-0.0.1.dist-info/METADATA
cybory-0.0.1.dist-info/WHEEL
cybory-0.0.1.dist-info/top_level.txt
cybory-0.0.1.dist-info/RECORD
