Metadata-Version: 2.1
Name: cybory
Version: 0.0.1
Summary: 半生物体操作系统
Home-page: https://github.com/tangtalang/cybory
Author: wangkun
Author-email: wangkun@lingzedongli.com
Classifier: Programming Language :: Python :: 3
Classifier: License :: OSI Approved :: MIT License
Classifier: Operating System :: OS Independent
Requires-Python: >=3.6
License-File: LICENSE
